{
	"info": {
		"_postman_id": "9635fcdf-3b04-4d09-9d00-b21722fd9aa9",
		"name": "Trello API Project",
		"schema": "https://schema.getpostman.com/json/collection/v2.1.0/collection.json",
		"_exporter_id": "37210911"
	},
	"item": [
		{
			"name": "Create Board",
			"event": [
				{
					"listen": "test",
					"script": {
						"exec": [
							"pm.test(\"Response Code is 200\", function () {\r",
							"    pm.response.to.have.status(200);\r",
							"});\r",
							"\r",
							"var jsonData = pm.response.json()\r",
							"pm.environment.set(\"Board_ID\", jsonData.id);"
						],
						"type": "text/javascript",
						"packages": {}
					}
				}
			],
			"request": {
				"method": "POST",
				"header": [],
				"body": {
					"mode": "raw",
					"raw": "",
					"options": {
						"raw": {
							"language": "json"
						}
					}
				},
				"url": {
					"raw": "{{Base_URL}}/1/boards?key={{Key}}&name=Postman_Board&token={{Token}}&defaultLists=false",
					"host": [
						"{{Base_URL}}"
					],
					"path": [
						"1",
						"boards"
					],
					"query": [
						{
							"key": "key",
							"value": "{{Key}}"
						},
						{
							"key": "name",
							"value": "Postman_Board"
						},
						{
							"key": "token",
							"value": "{{Token}}"
						},
						{
							"key": "defaultLists",
							"value": "false"
						}
					]
				}
			},
			"response": []
		},
		{
			"name": "Get Board",
			"event": [
				{
					"listen": "test",
					"script": {
						"exec": [
							"pm.test(\"Response Code is 200\", function () {\r",
							"    pm.response.to.have.status(200);\r",
							"});\r",
							""
						],
						"type": "text/javascript",
						"packages": {}
					}
				}
			],
			"request": {
				"method": "GET",
				"header": [],
				"url": {
					"raw": "{{Base_URL}}/1/boards/{{Board_ID}}?key={{Key}}&token={{Token}}",
					"host": [
						"{{Base_URL}}"
					],
					"path": [
						"1",
						"boards",
						"{{Board_ID}}"
					],
					"query": [
						{
							"key": "key",
							"value": "{{Key}}"
						},
						{
							"key": "token",
							"value": "{{Token}}"
						}
					]
				}
			},
			"response": []
		},
		{
			"name": "Create List",
			"event": [
				{
					"listen": "test",
					"script": {
						"exec": [
							"pm.test(\"Status code is 200\", function () {\r",
							"    pm.response.to.have.status(200);\r",
							"});\r",
							"\r",
							"var jsonData = pm.response.json()\r",
							"pm.environment.set(\"List_ID\", jsonData.id);"
						],
						"type": "text/javascript",
						"packages": {}
					}
				}
			],
			"request": {
				"method": "POST",
				"header": [],
				"url": {
					"raw": "{{Base_URL}}/1/lists?key={{Key}}&token={{Token}}&name=Postman_List4&idBoard={{Board_ID}}",
					"host": [
						"{{Base_URL}}"
					],
					"path": [
						"1",
						"lists"
					],
					"query": [
						{
							"key": "key",
							"value": "{{Key}}"
						},
						{
							"key": "token",
							"value": "{{Token}}"
						},
						{
							"key": "name",
							"value": "Postman_List4"
						},
						{
							"key": "idBoard",
							"value": "{{Board_ID}}"
						}
					]
				}
			},
			"response": []
		},
		{
			"name": "Get List",
			"event": [
				{
					"listen": "test",
					"script": {
						"exec": [
							"pm.test(\"Status code is 200\", function () {\r",
							"    pm.response.to.have.status(200);\r",
							"});"
						],
						"type": "text/javascript",
						"packages": {}
					}
				}
			],
			"request": {
				"method": "GET",
				"header": [],
				"url": {
					"raw": "{{Base_URL}}/1/lists/{{List_ID}}?key={{Key}}&token={{Token}}",
					"host": [
						"{{Base_URL}}"
					],
					"path": [
						"1",
						"lists",
						"{{List_ID}}"
					],
					"query": [
						{
							"key": "key",
							"value": "{{Key}}"
						},
						{
							"key": "token",
							"value": "{{Token}}"
						}
					]
				}
			},
			"response": []
		},
		{
			"name": "Get Board_Lists",
			"event": [
				{
					"listen": "test",
					"script": {
						"exec": [
							"pm.test(\"Status code is 200\", function () {\r",
							"    pm.response.to.have.status(200);\r",
							"});"
						],
						"type": "text/javascript",
						"packages": {}
					}
				}
			],
			"request": {
				"method": "GET",
				"header": [],
				"url": {
					"raw": "{{Base_URL}}/1/boards/{{Board_ID}}/lists?key={{Key}}&token={{Token}}",
					"host": [
						"{{Base_URL}}"
					],
					"path": [
						"1",
						"boards",
						"{{Board_ID}}",
						"lists"
					],
					"query": [
						{
							"key": "key",
							"value": "{{Key}}"
						},
						{
							"key": "token",
							"value": "{{Token}}"
						}
					]
				}
			},
			"response": []
		},
		{
			"name": "Create Card",
			"event": [
				{
					"listen": "test",
					"script": {
						"exec": [
							"pm.test(\"Status code is 200\", function () {\r",
							"    pm.response.to.have.status(200);\r",
							"});\r",
							"\r",
							"var jsonData = pm.response.json()\r",
							"pm.environment.set(\"Card_ID\", jsonData.id);"
						],
						"type": "text/javascript",
						"packages": {}
					}
				}
			],
			"request": {
				"method": "POST",
				"header": [],
				"url": {
					"raw": "{{Base_URL}}/1/cards?key={{Key}}&token={{Token}}&idList={{List_ID}}&name=Postman_Card",
					"host": [
						"{{Base_URL}}"
					],
					"path": [
						"1",
						"cards"
					],
					"query": [
						{
							"key": "key",
							"value": "{{Key}}"
						},
						{
							"key": "token",
							"value": "{{Token}}"
						},
						{
							"key": "idList",
							"value": "{{List_ID}}"
						},
						{
							"key": "name",
							"value": "Postman_Card"
						}
					]
				}
			},
			"response": []
		},
		{
			"name": "Get Card",
			"event": [
				{
					"listen": "test",
					"script": {
						"exec": [
							"pm.test(\"Status code is 200\", function () {\r",
							"    pm.response.to.have.status(200);\r",
							"});"
						],
						"type": "text/javascript",
						"packages": {}
					}
				}
			],
			"request": {
				"method": "GET",
				"header": [],
				"url": {
					"raw": "{{Base_URL}}/1/cards/{{Card_ID}}?key={{Key}}&token={{Token}}",
					"host": [
						"{{Base_URL}}"
					],
					"path": [
						"1",
						"cards",
						"{{Card_ID}}"
					],
					"query": [
						{
							"key": "key",
							"value": "{{Key}}"
						},
						{
							"key": "token",
							"value": "{{Token}}"
						}
					]
				}
			},
			"response": []
		},
		{
			"name": "Create CheckList",
			"event": [
				{
					"listen": "test",
					"script": {
						"exec": [
							"pm.test(\"Status code is 200\", function () {\r",
							"    pm.response.to.have.status(200);\r",
							"});\r",
							"\r",
							"var jsonData = pm.response.json()\r",
							"pm.environment.set(\"CheckList_ID\", jsonData.id);"
						],
						"type": "text/javascript",
						"packages": {}
					}
				}
			],
			"request": {
				"method": "POST",
				"header": [],
				"url": {
					"raw": "{{Base_URL}}/1/checklists?key={{Key}}&token={{Token}}&idCard={{Card_ID}}&name=Postman_Checklist2",
					"host": [
						"{{Base_URL}}"
					],
					"path": [
						"1",
						"checklists"
					],
					"query": [
						{
							"key": "key",
							"value": "{{Key}}"
						},
						{
							"key": "token",
							"value": "{{Token}}"
						},
						{
							"key": "idCard",
							"value": "{{Card_ID}}"
						},
						{
							"key": "name",
							"value": "Postman_Checklist2"
						}
					]
				}
			},
			"response": []
		},
		{
			"name": "Get CheckList",
			"event": [
				{
					"listen": "test",
					"script": {
						"exec": [
							"pm.test(\"Status code is 200\", function () {\r",
							"    pm.response.to.have.status(200);\r",
							"});"
						],
						"type": "text/javascript",
						"packages": {}
					}
				}
			],
			"request": {
				"method": "GET",
				"header": [],
				"url": {
					"raw": "{{Base_URL}}/1/checklists/{{CheckList_ID}}?key={{Key}}&token={{Token}}",
					"host": [
						"{{Base_URL}}"
					],
					"path": [
						"1",
						"checklists",
						"{{CheckList_ID}}"
					],
					"query": [
						{
							"key": "key",
							"value": "{{Key}}"
						},
						{
							"key": "token",
							"value": "{{Token}}"
						}
					]
				}
			},
			"response": []
		},
		{
			"name": "Delete CheckList",
			"event": [
				{
					"listen": "test",
					"script": {
						"exec": [
							"pm.test(\"Status code is 200\", function () {\r",
							"    pm.response.to.have.status(200);\r",
							"});"
						],
						"type": "text/javascript",
						"packages": {}
					}
				}
			],
			"request": {
				"method": "DELETE",
				"header": [],
				"url": {
					"raw": "{{Base_URL}}/1/checklists/{{CheckList_ID}}?key={{Key}}&token={{Token}}",
					"host": [
						"{{Base_URL}}"
					],
					"path": [
						"1",
						"checklists",
						"{{CheckList_ID}}"
					],
					"query": [
						{
							"key": "key",
							"value": "{{Key}}"
						},
						{
							"key": "token",
							"value": "{{Token}}"
						}
					]
				}
			},
			"response": []
		},
		{
			"name": "Delete Card",
			"event": [
				{
					"listen": "test",
					"script": {
						"exec": [
							"pm.test(\"Status code is 200\", function () {\r",
							"    pm.response.to.have.status(200);\r",
							"});"
						],
						"type": "text/javascript",
						"packages": {}
					}
				}
			],
			"request": {
				"method": "DELETE",
				"header": [],
				"url": {
					"raw": "{{Base_URL}}/1/cards/{{Card_ID}}?key={{Key}}&token={{Token}}",
					"host": [
						"{{Base_URL}}"
					],
					"path": [
						"1",
						"cards",
						"{{Card_ID}}"
					],
					"query": [
						{
							"key": "key",
							"value": "{{Key}}"
						},
						{
							"key": "token",
							"value": "{{Token}}"
						}
					]
				}
			},
			"response": []
		},
		{
			"name": "Archive List",
			"event": [
				{
					"listen": "test",
					"script": {
						"exec": [
							"pm.test(\"Status code is 200\", function () {\r",
							"    pm.response.to.have.status(200);\r",
							"});\r",
							""
						],
						"type": "text/javascript",
						"packages": {}
					}
				}
			],
			"request": {
				"method": "PUT",
				"header": [],
				"body": {
					"mode": "raw",
					"raw": "",
					"options": {
						"raw": {
							"language": "json"
						}
					}
				},
				"url": {
					"raw": "{{Base_URL}}/1/lists/{{List_ID}}/closed?key={{Key}}&token={{Token}}&value=true",
					"host": [
						"{{Base_URL}}"
					],
					"path": [
						"1",
						"lists",
						"{{List_ID}}",
						"closed"
					],
					"query": [
						{
							"key": "key",
							"value": "{{Key}}"
						},
						{
							"key": "token",
							"value": "{{Token}}"
						},
						{
							"key": "value",
							"value": "true"
						}
					]
				}
			},
			"response": []
		},
		{
			"name": "Delete Board",
			"event": [
				{
					"listen": "test",
					"script": {
						"exec": [
							"pm.test(\"Response Code is 200\", function () {\r",
							"    pm.response.to.have.status(200);\r",
							"});\r",
							"\r",
							""
						],
						"type": "text/javascript",
						"packages": {}
					}
				}
			],
			"request": {
				"method": "DELETE",
				"header": [],
				"url": {
					"raw": "{{Base_URL}}/1/boards/{{Board_ID}}?key={{Key}}&token={{Token}}",
					"host": [
						"{{Base_URL}}"
					],
					"path": [
						"1",
						"boards",
						"{{Board_ID}}"
					],
					"query": [
						{
							"key": "key",
							"value": "{{Key}}"
						},
						{
							"key": "token",
							"value": "{{Token}}"
						}
					]
				}
			},
			"response": []
		}
	],
	"event": [
		{
			"listen": "prerequest",
			"script": {
				"type": "text/javascript",
				"packages": {},
				"exec": [
					""
				]
			}
		},
		{
			"listen": "test",
			"script": {
				"type": "text/javascript",
				"packages": {},
				"exec": [
					"pm.test(\"Response time less than 3 seconds\", function () {\r",
					"    pm.expect(pm.response.responseTime).to.be.below(3000);\r",
					"});"
				]
			}
		}
	]
}